glMAC/__init__.py
glMAC/__main__.py
glMAC/glMAC.py
glMAC/mainwindow_rc.py
glMAC/mainwindow_ui.py
glMAC/images/QtIcon.png
glMAC/images/Screenshot_20180404_185505.png
glMAC/images/Screenshot_20180404_185733.png
glMAC/images/application-exit.svg
glMAC/images/glMAC_screenshot.png
glMAC/images/logo.png
glMAC/images/logo32x32.png
glMAC/resources/mainwindow.qrc
glMAC/resources/mainwindow.ui
glMAC-0.0.7.dist-info/METADATA
glMAC-0.0.7.dist-info/RECORD
glMAC-0.0.7.dist-info/WHEEL
glMAC-0.0.7.dist-info/entry_points.txt
glMAC-0.0.7.dist-info/top_level.txt
