Metadata-Version: 2.1
Name: glMAC
Version: 0.0.7
Summary: Retrieves vendor information from MAC address
Home-page: https://git.gallochri.com/gallochri/glMAC
Author: gallochri
Author-email: chri@gallochri.com
License: GPLv3
Download-URL: https://git.gallochri.com/gallochri/glMAC.git
Keywords: MAC,vendor,MAC Addresses
Platform: any
Classifier: Development Status :: 2 - Pre-Alpha
Classifier: Environment :: X11 Applications :: Qt
Classifier: Intended Audience :: End Users/Desktop
Classifier: License :: OSI Approved :: GNU General Public License v3 (GPLv3)
Classifier: Natural Language :: English
Classifier: Operating System :: OS Independent
Classifier: Programming Language :: Python :: 3.4
Classifier: Programming Language :: Python :: 3.5
Classifier: Programming Language :: Python :: 3.6
Classifier: Topic :: System
Classifier: Topic :: System :: Hardware
Provides: glMAC
Requires-Python: >=3.4
Requires-Dist: requests
Provides-Extra: dev
Requires-Dist: pyqt-distutils; extra == 'dev'
Requires-Dist: pypandoc; extra == 'dev'
Requires-Dist: twine; extra == 'dev'
Provides-Extra: test
Requires-Dist: coverage; extra == 'test'
